<task numberOfSnaps="25" stepsPerSnap="1">
	<system>
		<defaultContactCalculator type="AdhesionContactCalculator" />
		<contactThreshold measure="abs" value="0.4"/>
		<collisionDetector static="true" />
	</system>
	<bodies>
		<body id="cube1">
			<rheology type="elastic" />
			<mesh id="cube1" type="markered-mesh-geo" cellsNum="60" file="models/cube.geo" />
			<material id="testMaterial" />
			<transform type="translate" moveX="0" moveY="0" moveZ="-5.2" />
		</body>
		<body id="cube2">
			<rheology type="elastic" />
			<mesh id="cube2" type="markered-mesh-geo" cellsNum="60" file="models/cube.geo" />
			<material id="testMaterial" />
			<transform type="translate" moveX="0" moveY="0" moveZ="5.2" />
		</body>
	</bodies>
	<initialState>
		<area type="box" minX="-10" maxX="10" minY="-10" maxY="10" minZ="-3" maxZ="-1"/>
		<values vz="3" sxx="-700" syy="-700" szz="-900" />
	</initialState>
</task>
